onpay/signals.py
onpay/admin.py
onpay/forms.py
onpay/__init__.py
onpay/views.py
onpay/settings.py
onpay/utils.py
onpay/urls.py
onpay/models.py
onpay/tests/__init__.py
onpay/management/__init__.py
onpay/management/commands/find_expired_payments.py
onpay/management/commands/__init__.py
django_onpay-0.2.2.dist-info/metadata.json
django_onpay-0.2.2.dist-info/WHEEL
django_onpay-0.2.2.dist-info/METADATA
django_onpay-0.2.2.dist-info/DESCRIPTION.rst
django_onpay-0.2.2.dist-info/RECORD
django_onpay-0.2.2.dist-info/top_level.txt
