Metadata-Version: 2.0
Name: django-onpay
Version: 0.2.2
Summary: onpay
Home-page: http://pypi.python.org/pypi/django-onpay
Author: Mikhail Porokhovnichenko <marazmiki@gmail.com>
Author-email: marazmiki@gmail.com
License: MIT license
Download-URL: http://bitbucket.org/marazmiki/django-onpay/get/tip.zip
Platform: OS Independent
Classifier: Development Status :: 4 - Beta
Classifier: Environment :: Web Environment
Classifier: Intended Audience :: Developers
Classifier: License :: OSI Approved :: BSD License
Classifier: Operating System :: OS Independent
Classifier: Programming Language :: Python
Classifier: Framework :: Django
Requires-Dist: django
Requires-Dist: python-dateutil
Requires-Dist: six
